carml/__init__.py
carml/__main__.py
carml/carml_check_pypi.py
carml/carml_circ.py
carml/carml_cmd.py
carml/carml_copybin.py
carml/carml_events.py
carml/carml_graph.py
carml/carml_monitor.py
carml/carml_newid.py
carml/carml_onion.py
carml/carml_pastebin.py
carml/carml_readme.py
carml/carml_relay.py
carml/carml_stream.py
carml/carml_tbb.py
carml/carml_tmux.py
carml/carml_xplanet.py
carml/cli.py
carml/util.py
carml-23.11.1.data/data/share/carml/README.rst
carml-23.11.1.data/data/share/carml/meejah.asc
carml-23.11.1.data/data/share/carml/doc/command-checkpypi.rst
carml-23.11.1.data/data/share/carml/doc/command-circ.rst
carml-23.11.1.data/data/share/carml/doc/command-cmd.rst
carml-23.11.1.data/data/share/carml/doc/command-copybin.rst
carml-23.11.1.data/data/share/carml/doc/command-downloadbundle.rst
carml-23.11.1.data/data/share/carml/doc/command-events.rst
carml-23.11.1.data/data/share/carml/doc/command-monitor.rst
carml-23.11.1.data/data/share/carml/doc/command-newid.rst
carml-23.11.1.data/data/share/carml/doc/command-onion.rst
carml-23.11.1.data/data/share/carml/doc/command-pastebin.rst
carml-23.11.1.data/data/share/carml/doc/command-relay.rst
carml-23.11.1.data/data/share/carml/doc/command-stream.rst
carml-23.11.1.data/data/share/carml/doc/command-xplanet.rst
carml-23.11.1.data/data/share/carml/doc/commands.rst
carml-23.11.1.data/data/share/carml/doc/development.rst
carml-23.11.1.data/data/share/carml/doc/howtos.rst
carml-23.11.1.data/data/share/carml/doc/index.rst
carml-23.11.1.data/data/share/carml/doc/installation.rst
carml-23.11.1.data/data/share/carml/doc/releases.rst
carml-23.11.1.dist-info/LICENSE
carml-23.11.1.dist-info/METADATA
carml-23.11.1.dist-info/WHEEL
carml-23.11.1.dist-info/entry_points.txt
carml-23.11.1.dist-info/top_level.txt
carml-23.11.1.dist-info/RECORD
