Metadata-Version: 2.1
Name: carml
Version: 23.11.1
Summary: A command-line tool to query and control a running Tor. Based on txtorcon + Twisted.
Home-page: https://github.com/meejah/carml
Author: meejah
Author-email: meejah@meejah.ca
License: Public Domain (http://unlicense.org/)
Keywords: python,twisted,tor,command-line,cli
Classifier: Framework :: Twisted
Classifier: Development Status :: 4 - Beta
Classifier: Environment :: Console
Classifier: Intended Audience :: Developers
Classifier: License :: Public Domain
Classifier: Natural Language :: English
Classifier: Operating System :: POSIX :: Linux
Classifier: Operating System :: Unix
Classifier: Programming Language :: Python
Classifier: Programming Language :: Python :: 3
Classifier: Topic :: System :: Networking
Classifier: Topic :: Internet :: Proxy Servers
Classifier: Topic :: Internet
Classifier: Topic :: Security
Classifier: Topic :: Utilities
License-File: LICENSE
Requires-Dist: ansicolors ==1.1.8
Requires-Dist: attrs ==23.1.0
Requires-Dist: Automat ==22.10.0
Requires-Dist: cffi ==1.16.0
Requires-Dist: click ==8.1.7
Requires-Dist: constantly ==23.10.4
Requires-Dist: cryptography ==41.0.5
Requires-Dist: humanize ==4.8.0
Requires-Dist: hyperlink ==21.0.0
Requires-Dist: idna ==3.4
Requires-Dist: incremental ==22.10.0
Requires-Dist: pyasn1 ==0.5.0
Requires-Dist: pyasn1-modules ==0.3.0
Requires-Dist: pycparser ==2.21
Requires-Dist: pyOpenSSL ==23.3.0
Requires-Dist: service-identity ==23.1.0
Requires-Dist: setuptools ==65.5.0
Requires-Dist: six ==1.16.0
Requires-Dist: Twisted ==23.10.0
Requires-Dist: txtorcon ==23.11.0
Requires-Dist: typing-extensions ==4.8.0
Requires-Dist: zope.interface ==6.1
